{
  "task": [
    {
      "id": "6ab4",
      "task": "as"
    },
    {
      "id": "8c56",
      "task": "asdsds"
    },
    {
      "id": "59b7",
      "task": "asdsds"
    },
    {
      "id": "32ae",
      "task": "asdsds"
    },
    {
      "id": "8a73",
      "task": "asdsds"
    },
    {
      "id": "f1a1",
      "task": "asdsds"
    },
    {
      "id": "5410",
      "task": "asdsds"
    },
    {
      "id": "e466",
      "task": "asdsds"
    },
    {
      "id": "9839",
      "task": "asdsdsfs"
    },
    {
      "id": "5484",
      "task": "asdsdsfs"
    },
    {
      "id": "c3f9",
      "task": "asdsdsfs"
    },
    {
      "id": "c6b4",
      "task": "asdsdsfs"
    },
    {
      "id": "650b",
      "task": "as"
    },
    {
      "id": "4cdd",
      "task": "as"
    },
    {
      "id": "1bf7",
      "task": "as"
    },
    {
      "id": "60a2",
      "task": "asasd"
    },
    {
      "id": "eb56",
      "task": "asasd"
    },
    {
      "id": "fe6d",
      "task": "asasd"
    },
    {
      "id": "e137",
      "task": "asasd"
    },
    {
      "id": "4d57",
      "task": "asasd"
    },
    {
      "id": "0421",
      "task": "asasd"
    },
    {
      "id": "9416",
      "task": "asasdasd"
    },
    {
      "id": "4a8d",
      "task": "asasdasd"
    },
    {
      "id": "369e",
      "task": "asasdasd"
    },
    {
      "id": "457a",
      "task": "asasdasd"
    },
    {
      "id": "3bff",
      "task": "asasdasd"
    },
    {
      "id": "9cb3",
      "task": "asasdasd"
    },
    {
      "id": "3d49",
      "task": "asasdasd"
    },
    {
      "id": "8ff5",
      "task": "as"
    },
    {
      "id": "3924",
      "task": "as"
    },
    {
      "id": "34aa",
      "task": "as"
    },
    {
      "id": "b70f",
      "task": "as"
    },
    {
      "id": "ed25",
      "task": "as"
    },
    {
      "id": "304c",
      "task": "as"
    },
    {
      "id": "87f1",
      "task": "asd"
    }
  ]
}